[
    {
        "initial": "A",
        "cells": [
            {
                "key": "10000089",
                "value": "鞍山银行"
            },
            {
                "key": "10000090",
                "value": "奥地利中央合作银行"
            },
            {
                "key": "10000091",
                "value": "澳门清算行"
            },
            {
                "key": "10000092",
                "value": "澳新银行"
            },
            {
                "key": "10000333",
                "value": "安徽省农村信用社联合社"
            },
            {
                "key": "10000334",
                "value": "鞍山市商业银行"
            },
            {
                "key": "10000423",
                "value": "澳大利亚联邦银行"
            },
            {
                "key": "10000465",
                "value": "安徽省村镇银行"
            },
            {
                "key": "10000469",
                "value": "安徽省农村商业银行"
            }
        ]
    },
    {
        "initial": "B",
        "cells": [
            {
                "key": "10000062",
                "value": "北京农村商业银行股份有限公司"
            },
            {
                "key": "10000068",
                "value": "宝生村镇银行"
            },
            {
                "key": "10000093",
                "value": "巴伐利亚州银行"
            },
            {
                "key": "10000094",
                "value": "北京顺义银座村镇银行"
            },
            {
                "key": "10000095",
                "value": "本溪市商业银行"
            },
            {
                "key": "10000096",
                "value": "比利时富通银行"
            },
            {
                "key": "10000097",
                "value": "比利时联合银行"
            },
            {
                "key": "10000472",
                "value": "宝鸡市农村信用社"
            },
            {
                "key": "10000477",
                "value": "保定市城市信用合作社"
            },
            {
                "key": "10000480",
                "value": "北京农村信用社"
            },
            {
                "key": "10000481",
                "value": "保定市商业银行"
            },
            {
                "key": "10000482",
                "value": "北京村镇银行"
            },
            {
                "key": "10000483",
                "value": "本溪市商业银行"
            },
            {
                "key": "10000487",
                "value": "宝缔纲银行"
            },
            {
                "key": "221",
                "value": "渤海银行"
            },
            {
                "key": "321",
                "value": "包商银行"
            },
            {
                "key": "361",
                "value": "北京农商银行"
            },
            {
                "key": "49",
                "value": "北京银行"
            },
            {
                "key": "536",
                "value": "保定银行"
            }
        ]
    },
    {
        "initial": "C",
        "cells": [
            {
                "key": "10000033",
                "value": "沧州银行"
            },
            {
                "key": "10000063",
                "value": "长沙银行股份有限公司"
            },
            {
                "key": "10000087",
                "value": "成都农商银行"
            },
            {
                "key": "10000098",
                "value": "朝兴银行"
            },
            {
                "key": "10000099",
                "value": "城市商业银行"
            },
            {
                "key": "10000100",
                "value": "城市信用社"
            },
            {
                "key": "10000101",
                "value": "村镇银行"
            },
            {
                "key": "10000267",
                "value": "长治银行"
            },
            {
                "key": "10000395",
                "value": "創興銀行有限公司"
            },
            {
                "key": "10000429",
                "value": "测试"
            },
            {
                "key": "10000454",
                "value": "成都农村信用社"
            },
            {
                "key": "10000461",
                "value": "常州市农村信用社"
            },
            {
                "key": "10000464",
                "value": "常德市农村商业银行"
            },
            {
                "key": "10000470",
                "value": "沧州市商业银行"
            },
            {
                "key": "163",
                "value": "长沙银行"
            },
            {
                "key": "261",
                "value": "成都银行"
            },
            {
                "key": "502",
                "value": "承德银行"
            },
            {
                "key": "533",
                "value": "长安银行"
            },
            {
                "key": "581",
                "value": "朝阳银行"
            }
        ]
    },
    {
        "initial": "D",
        "cells": [
            {
                "key": "10000102",
                "value": "达州市商业银行"
            },
            {
                "key": "10000103",
                "value": "大华银行"
            },
            {
                "key": "10000104",
                "value": "大连银行"
            },
            {
                "key": "10000105",
                "value": "大同银行"
            },
            {
                "key": "10000106",
                "value": "大新银行"
            },
            {
                "key": "10000107",
                "value": "丹东市商业银行"
            },
            {
                "key": "10000108",
                "value": "丹东银行"
            },
            {
                "key": "10000109",
                "value": "德富泰银行"
            },
            {
                "key": "10000110",
                "value": "德国北德意志州银行"
            },
            {
                "key": "10000111",
                "value": "德国商业银行"
            },
            {
                "key": "10000112",
                "value": "德累斯顿银行"
            },
            {
                "key": "10000113",
                "value": "德阳银行"
            },
            {
                "key": "10000114",
                "value": "德意志银行"
            },
            {
                "key": "10000115",
                "value": "德州银行"
            },
            {
                "key": "10000116",
                "value": "第一商业银行"
            },
            {
                "key": "10000117",
                "value": "东京三菱银行"
            },
            {
                "key": "10000118",
                "value": "东营莱商村镇银行"
            },
            {
                "key": "10000119",
                "value": "东营银行"
            },
            {
                "key": "10000120",
                "value": "都江堰金都村镇银行"
            },
            {
                "key": "10000121",
                "value": "鄂尔多斯银行"
            },
            {
                "key": "10000399",
                "value": "大眾銀行(香港)有限公司"
            },
            {
                "key": "10000400",
                "value": "大生銀行有限公司"
            },
            {
                "key": "10000401",
                "value": "大有銀行有限公司"
            },
            {
                "key": "10000457",
                "value": "德州银行"
            },
            {
                "key": "10000463",
                "value": "东方汇理银行"
            },
            {
                "key": "10000474",
                "value": "大众银行"
            },
            {
                "key": "43",
                "value": "东莞农村商业银行"
            },
            {
                "key": "48",
                "value": "东莞银行"
            },
            {
                "key": "524",
                "value": "东亚银行"
            }
        ]
    },
    {
        "initial": "F",
        "cells": [
            {
                "key": "10000122",
                "value": "法国巴黎银行"
            },
            {
                "key": "10000123",
                "value": "法国里昂信贷银行"
            },
            {
                "key": "10000124",
                "value": "法国外贸银行"
            },
            {
                "key": "10000125",
                "value": "法国兴业银行"
            },
            {
                "key": "10000126",
                "value": "丰业银行"
            },
            {
                "key": "10000127",
                "value": "福建海峡银行"
            },
            {
                "key": "10000128",
                "value": "抚顺银行"
            },
            {
                "key": "10000129",
                "value": "阜新银行"
            },
            {
                "key": "10000130",
                "value": "富邦华一银行"
            },
            {
                "key": "10000297",
                "value": "佛山市农村商业银行"
            },
            {
                "key": "10000302",
                "value": "福建农村信用社农商银行"
            },
            {
                "key": "10000396",
                "value": "富邦銀行(香港)有限公司"
            },
            {
                "key": "10000406",
                "value": "福州农商行"
            },
            {
                "key": "301",
                "value": "富滇银行"
            }
        ]
    },
    {
        "initial": "G",
        "cells": [
            {
                "key": "10000008",
                "value": "广西北部湾银行股份有限公司"
            },
            {
                "key": "10000072",
                "value": "桂银村镇银行"
            },
            {
                "key": "10000131",
                "value": "赣州银行"
            },
            {
                "key": "10000132",
                "value": "固阳包商惠农村镇银行"
            },
            {
                "key": "10000133",
                "value": "广东顺德农村商业银行"
            },
            {
                "key": "10000135",
                "value": "广州农村商业银行"
            },
            {
                "key": "10000136",
                "value": "贵州银行"
            },
            {
                "key": "10000137",
                "value": "国家开发银行"
            },
            {
                "key": "10000138",
                "value": "国民银行"
            },
            {
                "key": "10000139",
                "value": "国泰君安证券股份有限公司"
            },
            {
                "key": "10000140",
                "value": "国泰世华商业银行"
            },
            {
                "key": "10000315",
                "value": "广东省农村信用社联合社"
            },
            {
                "key": "10000332",
                "value": "广西省桂林市资源县农村信用合作社"
            },
            {
                "key": "10000335",
                "value": "广西农村信用社"
            },
            {
                "key": "10000372",
                "value": "甘肃农村信用社"
            },
            {
                "key": "10000373",
                "value": "贵州省农村信用社联合社"
            },
            {
                "key": "10000432",
                "value": "古交市阜民村镇银行"
            },
            {
                "key": "10000468",
                "value": "广西省城市信用社"
            },
            {
                "key": "12",
                "value": "广东发展银行"
            },
            {
                "key": "183",
                "value": "广东华兴银行"
            },
            {
                "key": "382",
                "value": "桂林银行"
            },
            {
                "key": "461",
                "value": "甘肃银行"
            },
            {
                "key": "504",
                "value": "广东南粤银行"
            },
            {
                "key": "506",
                "value": "广州银行"
            },
            {
                "key": "61",
                "value": "贵阳银行"
            }
        ]
    },
    {
        "initial": "H",
        "cells": [
            {
                "key": "10000141",
                "value": "哈密市商业银行"
            },
            {
                "key": "10000142",
                "value": "海口联合农村商业银行"
            },
            {
                "key": "10000143",
                "value": "韩国产业银行"
            },
            {
                "key": "10000144",
                "value": "韩国企业银行"
            },
            {
                "key": "10000145",
                "value": "韩国外换银行"
            },
            {
                "key": "10000146",
                "value": "韩亚银行"
            },
            {
                "key": "10000147",
                "value": "荷兰合作银行"
            },
            {
                "key": "10000148",
                "value": "荷兰商业银行"
            },
            {
                "key": "10000149",
                "value": "恒生银行"
            },
            {
                "key": "10000150",
                "value": "衡水银行"
            },
            {
                "key": "10000151",
                "value": "湖北银行"
            },
            {
                "key": "10000152",
                "value": "湖州银行"
            },
            {
                "key": "10000153",
                "value": "花旗银行"
            },
            {
                "key": "10000154",
                "value": "华南商业银行"
            },
            {
                "key": "10000155",
                "value": "华侨银行"
            },
            {
                "key": "10000156",
                "value": "华融湘江银行"
            },
            {
                "key": "10000311",
                "value": "黑龙江省农村信用社"
            },
            {
                "key": "10000319",
                "value": "河北省农村信用社联合社"
            },
            {
                "key": "10000336",
                "value": "海南省农村信用社"
            },
            {
                "key": "10000337",
                "value": "湖北省农村信用社联合社"
            },
            {
                "key": "10000345",
                "value": "户县海丝村镇银行"
            },
            {
                "key": "10000346",
                "value": "河南省农村信用社"
            },
            {
                "key": "10000374",
                "value": "湖南省农村信用社联合社"
            },
            {
                "key": "10000382",
                "value": "河南巩义农村商业银行股份有限公司"
            },
            {
                "key": "10000427",
                "value": "河南永城农村商业银行股份有限公司"
            },
            {
                "key": "10000428",
                "value": "河南武陟农村商业银行股份有限公司"
            },
            {
                "key": "10000437",
                "value": "湖滨农商银行"
            },
            {
                "key": "10000450",
                "value": "湖南省农村商业银行"
            },
            {
                "key": "10000451",
                "value": "海南银行"
            },
            {
                "key": "10000473",
                "value": "湖州银行"
            },
            {
                "key": "10000484",
                "value": "华美银行"
            },
            {
                "key": "10000486",
                "value": "河北省农村商业银行"
            },
            {
                "key": "10000625",
                "value": "湖北省农村信用社"
            },
            {
                "key": "10000626",
                "value": "海南省农村信用社联合社"
            },
            {
                "key": "101",
                "value": "汉口银行"
            },
            {
                "key": "102",
                "value": "杭州联合农村商业银行"
            },
            {
                "key": "142",
                "value": "徽商银行"
            },
            {
                "key": "161",
                "value": "葫芦岛银行"
            },
            {
                "key": "401",
                "value": "邯郸银行"
            },
            {
                "key": "42",
                "value": "杭州银行"
            },
            {
                "key": "46",
                "value": "华夏银行"
            },
            {
                "key": "503",
                "value": "河北银行"
            },
            {
                "key": "508",
                "value": "葫芦岛市商业银行"
            },
            {
                "key": "526",
                "value": "哈尔滨银行股份有限公司"
            },
            {
                "key": "561",
                "value": "恒丰银行"
            }
        ]
    },
    {
        "initial": "J",
        "cells": [
            {
                "key": "10000016",
                "value": "江西银行"
            },
            {
                "key": "10000032",
                "value": "江苏长江商业银行"
            },
            {
                "key": "10000034",
                "value": "江苏江南农村商业银行股份有限公司"
            },
            {
                "key": "10000073",
                "value": "建阳村镇银行"
            },
            {
                "key": "10000075",
                "value": "建瓯村镇银行"
            },
            {
                "key": "10000158",
                "value": "吉林银行"
            },
            {
                "key": "10000159",
                "value": "集友银行"
            },
            {
                "key": "10000160",
                "value": "济宁银行"
            },
            {
                "key": "10000161",
                "value": "嘉兴银行"
            },
            {
                "key": "10000162",
                "value": "建东银行"
            },
            {
                "key": "10000163",
                "value": "江苏常熟农村商业银行"
            },
            {
                "key": "10000164",
                "value": "江苏江阴农村商业银行"
            },
            {
                "key": "10000165",
                "value": "江苏吴江农村商业银行"
            },
            {
                "key": "10000166",
                "value": "江西赣州银座村镇银行"
            },
            {
                "key": "10000168",
                "value": "九江银行"
            },
            {
                "key": "10000312",
                "value": "江苏省农村信用社联合社"
            },
            {
                "key": "10000313",
                "value": "江西省农村信用社联合社"
            },
            {
                "key": "10000327",
                "value": "江门新会农村商业银行股份有限公司"
            },
            {
                "key": "10000338",
                "value": "吉林农村信用社"
            },
            {
                "key": "10000339",
                "value": "江阴农商银行"
            },
            {
                "key": "10000378",
                "value": "江南农村商业银行"
            },
            {
                "key": "10000422",
                "value": "金谷农商行"
            },
            {
                "key": "10000433",
                "value": "吉林双阳农村商业银行"
            },
            {
                "key": "10000614",
                "value": "焦作市商业银行"
            },
            {
                "key": "10000623",
                "value": "吉林省农村信用社联合社"
            },
            {
                "key": "14",
                "value": "交通银行"
            },
            {
                "key": "182",
                "value": "锦州银行"
            },
            {
                "key": "241",
                "value": "江苏银行"
            },
            {
                "key": "383",
                "value": "晋中银行"
            },
            {
                "key": "523",
                "value": "晋商银行"
            },
            {
                "key": "534",
                "value": "晋城银行"
            },
            {
                "key": "621",
                "value": "金华银行"
            }
        ]
    },
    {
        "initial": "K",
        "cells": [
            {
                "key": "10000169",
                "value": "库尔勒市商业银行"
            },
            {
                "key": "10000170",
                "value": "昆仑银行"
            },
            {
                "key": "10000171",
                "value": "昆山农村商业银行"
            },
            {
                "key": "10000475",
                "value": "库尔勒银行"
            }
        ]
    },
    {
        "initial": "L",
        "cells": [
            {
                "key": "10000006",
                "value": "乐清农商银行"
            },
            {
                "key": "10000007",
                "value": "兰州银行"
            },
            {
                "key": "10000172",
                "value": "莱商银行"
            },
            {
                "key": "10000173",
                "value": "凉山州商业银行"
            },
            {
                "key": "10000174",
                "value": "辽阳银行"
            },
            {
                "key": "10000175",
                "value": "廖创兴银行"
            },
            {
                "key": "10000176",
                "value": "临商银行"
            },
            {
                "key": "10000177",
                "value": "柳州银行"
            },
            {
                "key": "10000178",
                "value": "泸州市商业银行"
            },
            {
                "key": "10000179",
                "value": "罗马银行"
            },
            {
                "key": "10000180",
                "value": "漯河市商业银行"
            },
            {
                "key": "10000310",
                "value": "辽宁省农村信用社联合社"
            },
            {
                "key": "10000344",
                "value": "临潼海丝村镇银行"
            },
            {
                "key": "10000417",
                "value": "灵宝市农村信用合作联社"
            },
            {
                "key": "10000430",
                "value": "洛阳农商银行"
            },
            {
                "key": "10000452",
                "value": "辽宁省城市信用社"
            },
            {
                "key": "122",
                "value": "廊坊银行"
            },
            {
                "key": "201",
                "value": "乐山市商业银行"
            },
            {
                "key": "262",
                "value": "洛阳银行"
            },
            {
                "key": "528",
                "value": "莱州农村商业银行"
            },
            {
                "key": "531",
                "value": "龙江银行"
            }
        ]
    },
    {
        "initial": "M",
        "cells": [
            {
                "key": "10000181",
                "value": "马来亚银行"
            },
            {
                "key": "10000182",
                "value": "美国银行"
            },
            {
                "key": "10000183",
                "value": "蒙特利尔银行"
            },
            {
                "key": "10000184",
                "value": "绵阳市商业银行"
            },
            {
                "key": "10000185",
                "value": "摩根大通银行"
            },
            {
                "key": "10000342",
                "value": "闽清瑞狮村镇银行"
            },
            {
                "key": "10000459",
                "value": "摩根士丹利国际银行"
            }
        ]
    },
    {
        "initial": "N",
        "cells": [
            {
                "key": "10000002",
                "value": "南海农商银行"
            },
            {
                "key": "10000039",
                "value": "南充市商业银行"
            },
            {
                "key": "10000186",
                "value": "南康赣商村镇银行"
            },
            {
                "key": "10000187",
                "value": "南阳银行"
            },
            {
                "key": "10000188",
                "value": "南洋商业银行"
            },
            {
                "key": "10000189",
                "value": "宁波东海银行"
            },
            {
                "key": "10000190",
                "value": "宁波通商银行"
            },
            {
                "key": "10000191",
                "value": "宁夏黄河农村商业银行"
            },
            {
                "key": "10000192",
                "value": "农村合作银行"
            },
            {
                "key": "10000193",
                "value": "农村信用联社"
            },
            {
                "key": "10000309",
                "value": "内蒙古自治区农村信用社联合社"
            },
            {
                "key": "10000387",
                "value": "农村信用合作社"
            },
            {
                "key": "10000398",
                "value": "興業銀行股份有限公司香港分行"
            },
            {
                "key": "10000455",
                "value": "内蒙古农村商业银行"
            },
            {
                "key": "121",
                "value": "宁夏银行股份有限公司"
            },
            {
                "key": "162",
                "value": "农村合作信用社"
            },
            {
                "key": "45",
                "value": "农村商业银行"
            },
            {
                "key": "47",
                "value": "南京银行"
            },
            {
                "key": "505",
                "value": "内蒙古银行"
            },
            {
                "key": "62",
                "value": "宁波银行"
            }
        ]
    },
    {
        "initial": "P",
        "cells": [
            {
                "key": "10000194",
                "value": "攀枝花市商业银行"
            },
            {
                "key": "10000195",
                "value": "盘谷银行"
            },
            {
                "key": "10000196",
                "value": "平顶山银行"
            },
            {
                "key": "10000197",
                "value": "平凉市商业银行"
            },
            {
                "key": "10000431",
                "value": "PayGate"
            },
            {
                "key": "11",
                "value": "平安银行"
            },
            {
                "key": "421",
                "value": "盘锦市商业银行"
            }
        ]
    },
    {
        "initial": "Q",
        "cells": [
            {
                "key": "10000037",
                "value": "其它银行"
            },
            {
                "key": "10000042",
                "value": "泉州银行"
            },
            {
                "key": "10000199",
                "value": "青岛国际银行"
            },
            {
                "key": "10000200",
                "value": "青海银行"
            },
            {
                "key": "10000201",
                "value": "琼海国民村镇银行"
            },
            {
                "key": "10000202",
                "value": "曲靖市商业银行"
            },
            {
                "key": "10000293",
                "value": "秦皇岛银行"
            },
            {
                "key": "10000347",
                "value": "泉州农商银行"
            },
            {
                "key": "10000375",
                "value": "青海省农村信用社联合社"
            },
            {
                "key": "281",
                "value": "青岛银行"
            },
            {
                "key": "403",
                "value": "齐鲁银行"
            },
            {
                "key": "535",
                "value": "秦皇岛市商业银行"
            },
            {
                "key": "641",
                "value": "齐商银行"
            }
        ]
    },
    {
        "initial": "R",
        "cells": [
            {
                "key": "10000204",
                "value": "瑞典北欧斯安银行"
            },
            {
                "key": "10000205",
                "value": "瑞典商业银行公共有限公司"
            },
            {
                "key": "10000206",
                "value": "瑞典银行"
            },
            {
                "key": "10000207",
                "value": "瑞士信贷第一波士顿银行"
            },
            {
                "key": "10000208",
                "value": "瑞士银行"
            },
            {
                "key": "10000209",
                "value": "瑞穗银行"
            },
            {
                "key": "501",
                "value": "日照银行"
            }
        ]
    },
    {
        "initial": "S",
        "cells": [
            {
                "key": "10000011",
                "value": "山东济南润丰农村合作银行"
            },
            {
                "key": "10000076",
                "value": "石狮农商行"
            },
            {
                "key": "10000210",
                "value": "三井住友银行"
            },
            {
                "key": "10000211",
                "value": "三门峡市商业银行"
            },
            {
                "key": "10000214",
                "value": "山口银行"
            },
            {
                "key": "10000215",
                "value": "商丘市商业银行"
            },
            {
                "key": "10000216",
                "value": "上海—巴黎国际银行"
            },
            {
                "key": "10000217",
                "value": "上海崇明长江村镇银行"
            },
            {
                "key": "10000218",
                "value": "上海商业银行"
            },
            {
                "key": "10000219",
                "value": "上饶银行"
            },
            {
                "key": "10000220",
                "value": "绍兴银行"
            },
            {
                "key": "10000221",
                "value": "深圳福田银座村镇银行"
            },
            {
                "key": "10000222",
                "value": "石嘴山银行"
            },
            {
                "key": "10000223",
                "value": "首都银行"
            },
            {
                "key": "10000224",
                "value": "苏格兰皇家银行"
            },
            {
                "key": "10000225",
                "value": "遂宁市商业银行"
            },
            {
                "key": "10000292",
                "value": "深圳农村商业银行"
            },
            {
                "key": "10000314",
                "value": "山东省农村信用社联合社"
            },
            {
                "key": "10000318",
                "value": "陕西省农村信用社联合社"
            },
            {
                "key": "10000320",
                "value": "山西省农村信用社联合社"
            },
            {
                "key": "10000343",
                "value": "三原海丝村镇银行"
            },
            {
                "key": "10000348",
                "value": "陕西秦农农村商业银行股份有限公司"
            },
            {
                "key": "10000352",
                "value": "遂宁银行"
            },
            {
                "key": "10000357",
                "value": "双流诚民村镇银行有限责任公司"
            },
            {
                "key": "10000404",
                "value": "三河蒙银村镇银行"
            },
            {
                "key": "10000631",
                "value": "四川省农村信用社联合社"
            },
            {
                "key": "141",
                "value": "上海银行"
            },
            {
                "key": "44",
                "value": "苏州银行"
            },
            {
                "key": "442",
                "value": "盛京银行"
            },
            {
                "key": "525",
                "value": "商业银行"
            },
            {
                "key": "530",
                "value": "石狮农商银行"
            },
            {
                "key": "8",
                "value": "上海浦东发展银行"
            },
            {
                "key": "81",
                "value": "上海农商银行"
            }
        ]
    },
    {
        "initial": "T",
        "cells": [
            {
                "key": "10000226",
                "value": "太仓农村商业银行"
            },
            {
                "key": "10000227",
                "value": "泰安银行"
            },
            {
                "key": "10000228",
                "value": "泰华农民银行"
            },
            {
                "key": "10000229",
                "value": "唐山银行"
            },
            {
                "key": "10000230",
                "value": "天津滨海农村商业银行"
            },
            {
                "key": "10000231",
                "value": "天津农村商业银行"
            },
            {
                "key": "10000232",
                "value": "天津市蓟县村镇银行"
            },
            {
                "key": "10000233",
                "value": "铁岭银行"
            },
            {
                "key": "10000377",
                "value": "天津市农村信用合作社"
            },
            {
                "key": "125",
                "value": "台州银行股份有限公司"
            },
            {
                "key": "381",
                "value": "天津银行"
            },
            {
                "key": "41",
                "value": "台州商业银行"
            },
            {
                "key": "529",
                "value": "泰安市商业银行"
            }
        ]
    },
    {
        "initial": "W",
        "cells": [
            {
                "key": "10000001",
                "value": "芜湖津盛农村商业银行股份有限公司"
            },
            {
                "key": "10000026",
                "value": "武汉农村商业银行"
            },
            {
                "key": "10000234",
                "value": "威海市商业银行"
            },
            {
                "key": "10000235",
                "value": "温州银行"
            },
            {
                "key": "10000236",
                "value": "文昌国民村镇银行"
            },
            {
                "key": "10000237",
                "value": "乌鲁木齐银行"
            },
            {
                "key": "10000238",
                "value": "无锡农村商业银行"
            },
            {
                "key": "10000405",
                "value": "微众银行"
            },
            {
                "key": "522",
                "value": "乌海银行"
            },
            {
                "key": "527",
                "value": "潍坊银行"
            }
        ]
    },
    {
        "initial": "X",
        "cells": [
            {
                "key": "10",
                "value": "兴业银行"
            },
            {
                "key": "10000079",
                "value": "仙游村镇银行"
            },
            {
                "key": "10000212",
                "value": "厦门国际银行"
            },
            {
                "key": "10000213",
                "value": "厦门银行"
            },
            {
                "key": "10000239",
                "value": "西藏银行"
            },
            {
                "key": "10000240",
                "value": "西德意志银行"
            },
            {
                "key": "10000241",
                "value": "香港清算行"
            },
            {
                "key": "10000242",
                "value": "湘乡市村镇银行"
            },
            {
                "key": "10000243",
                "value": "新韩银行"
            },
            {
                "key": "10000245",
                "value": "新疆汇和银行"
            },
            {
                "key": "10000247",
                "value": "修水九银村镇银行"
            },
            {
                "key": "10000376",
                "value": "新疆维吾尔自治区农村信用社联合社"
            },
            {
                "key": "10000407",
                "value": "香港印度银行"
            },
            {
                "key": "10000413",
                "value": "新疆农村商业银行"
            },
            {
                "key": "10000442",
                "value": "厦门农商银行"
            },
            {
                "key": "10000453",
                "value": "新乡银行"
            },
            {
                "key": "402",
                "value": "香港上海汇丰银行"
            },
            {
                "key": "481",
                "value": "香港星展銀行"
            },
            {
                "key": "521",
                "value": "邢台银行"
            },
            {
                "key": "601",
                "value": "西安银行"
            }
        ]
    },
    {
        "initial": "Y",
        "cells": [
            {
                "key": "10000027",
                "value": "伊川农商银行"
            },
            {
                "key": "10000040",
                "value": "洋县农村信用合作联社"
            },
            {
                "key": "10000080",
                "value": "永定村镇银行"
            },
            {
                "key": "10000248",
                "value": "雅安市商业银行"
            },
            {
                "key": "10000249",
                "value": "亚洲商业银行"
            },
            {
                "key": "10000250",
                "value": "烟台银行"
            },
            {
                "key": "10000251",
                "value": "阳泉市商业银行"
            },
            {
                "key": "10000252",
                "value": "宜宾市商业银行"
            },
            {
                "key": "10000253",
                "value": "宜兴阳羡村镇银行"
            },
            {
                "key": "10000254",
                "value": "意大利联合圣保罗银行"
            },
            {
                "key": "10000255",
                "value": "银行间市场清算所"
            },
            {
                "key": "10000256",
                "value": "鄞州银行"
            },
            {
                "key": "10000257",
                "value": "英国巴克莱银行"
            },
            {
                "key": "10000258",
                "value": "永亨银行"
            },
            {
                "key": "10000259",
                "value": "永隆银行"
            },
            {
                "key": "10000260",
                "value": "友利银行"
            },
            {
                "key": "10000261",
                "value": "玉溪市商业银行"
            },
            {
                "key": "10000307",
                "value": "营口沿海银行"
            },
            {
                "key": "10000316",
                "value": "云南省农村信用社联合社"
            },
            {
                "key": "10000362",
                "value": "郾城包商村镇银行"
            },
            {
                "key": "10000458",
                "value": "裕信银行"
            },
            {
                "key": "10000460",
                "value": "扬州市农村信用社"
            },
            {
                "key": "507",
                "value": "营口银行"
            }
        ]
    },
    {
        "initial": "Z",
        "cells": [
            {
                "key": "2",
                "value": "中国银行"
            },
            {
                "key": "1",
                "value": "中国工商银行"
            },
            {
                "key": "3",
                "value": "中国建设银行"
            },
            {
                "key": "4",
                "value": "中国农业银行"
            },
            {
                "key": "6",
                "value": "中国邮政储蓄银行"
            },
            {
                "key": "5",
                "value": "招商银行"
            },
            {
                "key": "7",
                "value": "中国光大银行"
            },
            {
                "key": "13",
                "value": "中信银行"
            },
            {
                "key": "15",
                "value": "中国民生银行"
            },
            {
                "key": "10000021",
                "value": "浙商银行"
            },
            {
                "key": "10000047",
                "value": "浙江银行股份有限公司"
            },
            {
                "key": "10000052",
                "value": "浙江农商银行"
            },
            {
                "key": "10000057",
                "value": "渣打银行"
            },
            {
                "key": "10000082",
                "value": "驻马店银行股份有限公司"
            },
            {
                "key": "10000262",
                "value": "枣庄银行"
            },
            {
                "key": "10000263",
                "value": "湛江市商业银行"
            },
            {
                "key": "10000264",
                "value": "张家港农村商业银行"
            },
            {
                "key": "10000265",
                "value": "张家口银行"
            },
            {
                "key": "10000266",
                "value": "彰化商业银行"
            },
            {
                "key": "10000268",
                "value": "浙江稠州商业银行"
            },
            {
                "key": "10000269",
                "value": "浙江景宁银座村镇银行"
            },
            {
                "key": "10000270",
                "value": "浙江民泰商业银行"
            },
            {
                "key": "10000271",
                "value": "浙江三门银座村镇银行"
            },
            {
                "key": "10000272",
                "value": "支付宝"
            },
            {
                "key": "10000273",
                "value": "支付业务收费专户"
            },
            {
                "key": "10000274",
                "value": "中德住房储蓄银行"
            },
            {
                "key": "10000275",
                "value": "中国进出口银行"
            },
            {
                "key": "10000276",
                "value": "中国农业发展银行"
            },
            {
                "key": "10000277",
                "value": "中国银行间外汇交易中心"
            },
            {
                "key": "10000278",
                "value": "中国银联"
            },
            {
                "key": "10000279",
                "value": "中信银行国际"
            },
            {
                "key": "10000280",
                "value": "中央国债登记结算有限责任公司"
            },
            {
                "key": "10000282",
                "value": "重庆农村商业银行"
            },
            {
                "key": "10000283",
                "value": "重庆黔江银座村镇银行"
            },
            {
                "key": "10000284",
                "value": "重庆三峡银行"
            },
            {
                "key": "10000285",
                "value": "重庆银行"
            },
            {
                "key": "10000286",
                "value": "重庆渝北银座村镇银行"
            },
            {
                "key": "10000287",
                "value": "珠海华润银行"
            },
            {
                "key": "10000288",
                "value": "珠海南通银行"
            },
            {
                "key": "10000289",
                "value": "自贡市商业银行"
            },
            {
                "key": "10000317",
                "value": "浙江省农村信用社联合社"
            },
            {
                "key": "10000353",
                "value": "中山农村商业银行"
            },
            {
                "key": "10000368",
                "value": "正定农商行"
            },
            {
                "key": "10000393",
                "value": "中國銀行(香港)有限公司"
            },
            {
                "key": "10000394",
                "value": "中國建設銀行(亞洲)股份有限公司"
            },
            {
                "key": "10000397",
                "value": "中國工商銀行(亞洲)有限公司"
            },
            {
                "key": "10000476",
                "value": "镇平农信"
            },
            {
                "key": "123",
                "value": "珠海农村商业银行"
            },
            {
                "key": "181",
                "value": "浙江泰隆商业银行"
            },
            {
                "key": "341",
                "value": "兆丰村镇银行"
            },
            {
                "key": "422",
                "value": "中原银行"
            },
            {
                "key": "441",
                "value": "郑州银行"
            },
            {
                "key": "443",
                "value": "张家口市商业银行"
            }
        ]
    }
]