[
  {
    "nodeId": "rootmenu",
    "parentNodeId": "-menu",
    "privilegeCode": "root",
    "privilegeName": "根节点",
    "isParent": "TRUE",
    "type": "menu",
    "checked": "TRUE",
    "id": "rootmenu",
    "parentId": "-menu",
    "text": "根节点",
    "children": [
      {
        "nodeId": "adminmenu",
        "parentNodeId": "rootmenu",
        "privilegeCode": "admin",
        "privilegeName": "权限管理",
        "isParent": "TRUE",
        "type": "menu",
        "checked": "TRUE",
        "id": "adminmenu",
        "parentId": "rootmenu",
        "text": "权限管理",
        "children": [
          {
            "nodeId": "rolemenu",
            "parentNodeId": "adminmenu",
            "privilegeCode": "role",
            "privilegeName": "角色管理",
            "isParent": "FALSE",
            "type": "menu",
            "checked": "TRUE",
            "id": "rolemenu",
            "parentId": "adminmenu",
            "text": "角色管理",
            "children": [
              {
                "nodeId": "role_addfunction",
                "parentNodeId": "rolemenu",
                "privilegeCode": "role_add",
                "privilegeName": "新增",
                "isParent": "FALSE",
                "type": "function",
                "checked": "TRUE",
                "id": "role_addfunction",
                "parentId": "rolemenu",
                "text": "新增",
                "children": []
              },
              {
                "nodeId": "role_editfunction",
                "parentNodeId": "rolemenu",
                "privilegeCode": "role_edit",
                "privilegeName": "修改",
                "isParent": "FALSE",
                "type": "function",
                "checked": "TRUE",
                "id": "role_editfunction",
                "parentId": "rolemenu",
                "text": "修改",
                "children": []
              },
              {
                "nodeId": "role_pagefunction",
                "parentNodeId": "rolemenu",
                "privilegeCode": "role_page",
                "privilegeName": "分页查询",
                "isParent": "FALSE",
                "type": "function",
                "checked": "FALSE",
                "id": "role_pagefunction",
                "parentId": "rolemenu",
                "text": "分页查询",
                "children": []
              },
              {
                "nodeId": "role_deletefunction",
                "parentNodeId": "rolemenu",
                "privilegeCode": "role_delete",
                "privilegeName": "删除",
                "isParent": "FALSE",
                "type": "function",
                "checked": "FALSE",
                "id": "role_deletefunction",
                "parentId": "rolemenu",
                "text": "删除",
                "children": []
              },
              {
                "nodeId": "role_privilege_editfunction",
                "parentNodeId": "rolemenu",
                "privilegeCode": "role_privilege_edit",
                "privilegeName": "权限配置",
                "isParent": "FALSE",
                "type": "function",
                "checked": "FALSE",
                "id": "role_privilege_editfunction",
                "parentId": "rolemenu",
                "text": "权限配置",
                "children": []
              },
              {
                "nodeId": "role_privilege_treefunction",
                "parentNodeId": "rolemenu",
                "privilegeCode": "role_privilege_tree",
                "privilegeName": "权限树查询",
                "isParent": "FALSE",
                "type": "function",
                "checked": "FALSE",
                "id": "role_privilege_treefunction",
                "parentId": "rolemenu",
                "text": "权限树查询",
                "children": []
              }
            ]
          },
          {
            "nodeId": "usermenu",
            "parentNodeId": "adminmenu",
            "privilegeCode": "user",
            "privilegeName": "用户管理",
            "isParent": "FALSE",
            "type": "menu",
            "checked": "FALSE",
            "id": "usermenu",
            "parentId": "adminmenu",
            "text": "用户管理",
            "children": [
              {
                "nodeId": "user_addfunction",
                "parentNodeId": "usermenu",
                "privilegeCode": "user_add",
                "privilegeName": "新增",
                "isParent": "FALSE",
                "type": "function",
                "checked": "FALSE",
                "id": "user_addfunction",
                "parentId": "usermenu",
                "text": "新增",
                "children": []
              },
              {
                "nodeId": "user_editfunction",
                "parentNodeId": "usermenu",
                "privilegeCode": "user_edit",
                "privilegeName": "修改",
                "isParent": "FALSE",
                "type": "function",
                "checked": "FALSE",
                "id": "user_editfunction",
                "parentId": "usermenu",
                "text": "修改",
                "children": []
              },
              {
                "nodeId": "user_pagefunction",
                "parentNodeId": "usermenu",
                "privilegeCode": "user_page",
                "privilegeName": "分页查询",
                "isParent": "FALSE",
                "type": "function",
                "checked": "FALSE",
                "id": "user_pagefunction",
                "parentId": "usermenu",
                "text": "分页查询",
                "children": []
              },
              {
                "nodeId": "user_deletefunction",
                "parentNodeId": "usermenu",
                "privilegeCode": "user_delete",
                "privilegeName": "删除",
                "isParent": "FALSE",
                "type": "function",
                "checked": "FALSE",
                "id": "user_deletefunction",
                "parentId": "usermenu",
                "text": "删除",
                "children": []
              },
              {
                "nodeId": "user_role_editfunction",
                "parentNodeId": "usermenu",
                "privilegeCode": "user_role_edit",
                "privilegeName": "配置角色",
                "isParent": "FALSE",
                "type": "function",
                "checked": "FALSE",
                "id": "user_role_editfunction",
                "parentId": "usermenu",
                "text": "配置角色",
                "children": []
              }
            ]
          },
          {
            "nodeId": "menumenu",
            "parentNodeId": "adminmenu",
            "privilegeCode": "menu",
            "privilegeName": "菜单管理",
            "isParent": "FALSE",
            "type": "menu",
            "checked": "FALSE",
            "id": "menumenu",
            "parentId": "adminmenu",
            "text": "菜单管理",
            "children": [
              {
                "nodeId": "menu_addfunction",
                "parentNodeId": "menumenu",
                "privilegeCode": "menu_add",
                "privilegeName": "新增",
                "isParent": "FALSE",
                "type": "function",
                "checked": "FALSE",
                "id": "menu_addfunction",
                "parentId": "menumenu",
                "text": "新增",
                "children": []
              },
              {
                "nodeId": "menu_editfunction",
                "parentNodeId": "menumenu",
                "privilegeCode": "menu_edit",
                "privilegeName": "修改",
                "isParent": "FALSE",
                "type": "function",
                "checked": "FALSE",
                "id": "menu_editfunction",
                "parentId": "menumenu",
                "text": "修改",
                "children": []
              },
              {
                "nodeId": "menu_deletefunction",
                "parentNodeId": "menumenu",
                "privilegeCode": "menu_delete",
                "privilegeName": "删除",
                "isParent": "FALSE",
                "type": "function",
                "checked": "FALSE",
                "id": "menu_deletefunction",
                "parentId": "menumenu",
                "text": "删除",
                "children": []
              },
              {
                "nodeId": "menu_treefunction",
                "parentNodeId": "menumenu",
                "privilegeCode": "menu_tree",
                "privilegeName": "菜单管理查询",
                "isParent": "FALSE",
                "type": "function",
                "checked": "FALSE",
                "id": "menu_treefunction",
                "parentId": "menumenu",
                "text": "菜单管理查询",
                "children": []
              },
              {
                "nodeId": "menu_function_addfunction",
                "parentNodeId": "menumenu",
                "privilegeCode": "menu_function_add",
                "privilegeName": "新增功能",
                "isParent": "FALSE",
                "type": "function",
                "checked": "FALSE",
                "id": "menu_function_addfunction",
                "parentId": "menumenu",
                "text": "新增功能",
                "children": []
              },
              {
                "nodeId": "menu_function_editfunction",
                "parentNodeId": "menumenu",
                "privilegeCode": "menu_function_edit",
                "privilegeName": "修改功能",
                "isParent": "FALSE",
                "type": "function",
                "checked": "FALSE",
                "id": "menu_function_editfunction",
                "parentId": "menumenu",
                "text": "修改功能",
                "children": []
              },
              {
                "nodeId": "menu_function_pagefunction",
                "parentNodeId": "menumenu",
                "privilegeCode": "menu_function_page",
                "privilegeName": "分页查询功能",
                "isParent": "FALSE",
                "type": "function",
                "checked": "FALSE",
                "id": "menu_function_pagefunction",
                "parentId": "menumenu",
                "text": "分页查询功能",
                "children": []
              },
              {
                "nodeId": "menu_function_deletefunction",
                "parentNodeId": "menumenu",
                "privilegeCode": "menu_function_delete",
                "privilegeName": "删除",
                "isParent": "FALSE",
                "type": "function",
                "checked": "FALSE",
                "id": "menu_function_deletefunction",
                "parentId": "menumenu",
                "text": "删除",
                "children": []
              }
            ]
          }
        ]
      },
      {
        "nodeId": "agent-mgmenu",
        "parentNodeId": "rootmenu",
        "privilegeCode": "agent-mg",
        "privilegeName": "我的合伙人",
        "isParent": "TRUE",
        "type": "menu",
        "checked": "FALSE",
        "id": "agent-mgmenu",
        "parentId": "rootmenu",
        "text": "我的合伙人",
        "children": [
          {
            "nodeId": "agentmenu",
            "parentNodeId": "agent-mgmenu",
            "privilegeCode": "agent",
            "privilegeName": "合伙人管理",
            "isParent": "FALSE",
            "type": "menu",
            "checked": "FALSE",
            "id": "agentmenu",
            "parentId": "agent-mgmenu",
            "text": "合伙人管理",
            "children": [
              {
                "nodeId": "agent_addfunction",
                "parentNodeId": "agentmenu",
                "privilegeCode": "agent_add",
                "privilegeName": "新增",
                "isParent": "FALSE",
                "type": "function",
                "checked": "FALSE",
                "id": "agent_addfunction",
                "parentId": "agentmenu",
                "text": "新增",
                "children": []
              },
              {
                "nodeId": "agent_editfunction",
                "parentNodeId": "agentmenu",
                "privilegeCode": "agent_edit",
                "privilegeName": "修改",
                "isParent": "FALSE",
                "type": "function",
                "checked": "FALSE",
                "id": "agent_editfunction",
                "parentId": "agentmenu",
                "text": "修改",
                "children": []
              },
              {
                "nodeId": "agent_pagefunction",
                "parentNodeId": "agentmenu",
                "privilegeCode": "agent_page",
                "privilegeName": "分页查询",
                "isParent": "FALSE",
                "type": "function",
                "checked": "FALSE",
                "id": "agent_pagefunction",
                "parentId": "agentmenu",
                "text": "分页查询",
                "children": []
              },
              {
                "nodeId": "agent_deletefunction",
                "parentNodeId": "agentmenu",
                "privilegeCode": "agent_delete",
                "privilegeName": "删除",
                "isParent": "FALSE",
                "type": "function",
                "checked": "FALSE",
                "id": "agent_deletefunction",
                "parentId": "agentmenu",
                "text": "删除",
                "children": []
              }
            ]
          },
          {
            "nodeId": "agent_transfermenu",
            "parentNodeId": "agent-mgmenu",
            "privilegeCode": "agent_transfer",
            "privilegeName": "合伙人转移",
            "isParent": "FALSE",
            "type": "menu",
            "checked": "FALSE",
            "id": "agent_transfermenu",
            "parentId": "agent-mgmenu",
            "text": "合伙人转移",
            "children": []
          }
        ]
      },
      {
        "nodeId": "qr_code_managemenu",
        "parentNodeId": "rootmenu",
        "privilegeCode": "qr_code_manage",
        "privilegeName": "我的授权码",
        "isParent": "TRUE",
        "type": "menu",
        "checked": "FALSE",
        "id": "qr_code_managemenu",
        "parentId": "rootmenu",
        "text": "我的授权码",
        "children": [
          {
            "nodeId": "qr_code_recieptmenu",
            "parentNodeId": "qr_code_managemenu",
            "privilegeCode": "qr_code_reciept",
            "privilegeName": "授权码采购",
            "isParent": "FALSE",
            "type": "menu",
            "checked": "FALSE",
            "id": "qr_code_recieptmenu",
            "parentId": "qr_code_managemenu",
            "text": "授权码采购",
            "children": [
              {
                "nodeId": "qr_code_reciept_addfunction",
                "parentNodeId": "qr_code_recieptmenu",
                "privilegeCode": "qr_code_reciept_add",
                "privilegeName": "新增",
                "isParent": "FALSE",
                "type": "function",
                "checked": "FALSE",
                "id": "qr_code_reciept_addfunction",
                "parentId": "qr_code_recieptmenu",
                "text": "新增",
                "children": []
              },
              {
                "nodeId": "qr_code_reciept_editfunction",
                "parentNodeId": "qr_code_recieptmenu",
                "privilegeCode": "qr_code_reciept_edit",
                "privilegeName": "修改",
                "isParent": "FALSE",
                "type": "function",
                "checked": "FALSE",
                "id": "qr_code_reciept_editfunction",
                "parentId": "qr_code_recieptmenu",
                "text": "修改",
                "children": []
              },
              {
                "nodeId": "qr_code_reciept_pagefunction",
                "parentNodeId": "qr_code_recieptmenu",
                "privilegeCode": "qr_code_reciept_page",
                "privilegeName": "分页查询",
                "isParent": "FALSE",
                "type": "function",
                "checked": "FALSE",
                "id": "qr_code_reciept_pagefunction",
                "parentId": "qr_code_recieptmenu",
                "text": "分页查询",
                "children": []
              },
              {
                "nodeId": "qr_code_reciept_downloadfunction",
                "parentNodeId": "qr_code_recieptmenu",
                "privilegeCode": "qr_code_reciept_download",
                "privilegeName": "下载",
                "isParent": "FALSE",
                "type": "function",
                "checked": "FALSE",
                "id": "qr_code_reciept_downloadfunction",
                "parentId": "qr_code_recieptmenu",
                "text": "下载",
                "children": []
              }
            ]
          },
          {
            "nodeId": "qrcodemenu",
            "parentNodeId": "qr_code_managemenu",
            "privilegeCode": "qrcode",
            "privilegeName": "授权码管理",
            "isParent": "FALSE",
            "type": "menu",
            "checked": "FALSE",
            "id": "qrcodemenu",
            "parentId": "qr_code_managemenu",
            "text": "授权码管理",
            "children": [
              {
                "nodeId": "qrcodebatch_addfunction",
                "parentNodeId": "qrcodemenu",
                "privilegeCode": "qrcodebatch_add",
                "privilegeName": "生成授权码",
                "isParent": "FALSE",
                "type": "function",
                "checked": "FALSE",
                "id": "qrcodebatch_addfunction",
                "parentId": "qrcodemenu",
                "text": "生成授权码",
                "children": []
              },
              {
                "nodeId": "qrcode_pagefunction",
                "parentNodeId": "qrcodemenu",
                "privilegeCode": "qrcode_page",
                "privilegeName": "分页查询",
                "isParent": "FALSE",
                "type": "function",
                "checked": "FALSE",
                "id": "qrcode_pagefunction",
                "parentId": "qrcodemenu",
                "text": "分页查询",
                "children": []
              },
              {
                "nodeId": "qrcode_editfunction",
                "parentNodeId": "qrcodemenu",
                "privilegeCode": "qrcode_edit",
                "privilegeName": "修改",
                "isParent": "FALSE",
                "type": "function",
                "checked": "FALSE",
                "id": "qrcode_editfunction",
                "parentId": "qrcodemenu",
                "text": "修改",
                "children": []
              },
              {
                "nodeId": "qrcode_bindfunction",
                "parentNodeId": "qrcodemenu",
                "privilegeCode": "qrcode_bind",
                "privilegeName": "绑定",
                "isParent": "FALSE",
                "type": "function",
                "checked": "FALSE",
                "id": "qrcode_bindfunction",
                "parentId": "qrcodemenu",
                "text": "绑定",
                "children": []
              },
              {
                "nodeId": "qrcode_unbindfunction",
                "parentNodeId": "qrcodemenu",
                "privilegeCode": "qrcode_unbind",
                "privilegeName": "解绑",
                "isParent": "FALSE",
                "type": "function",
                "checked": "FALSE",
                "id": "qrcode_unbindfunction",
                "parentId": "qrcodemenu",
                "text": "解绑",
                "children": []
              },
              {
                "nodeId": "qrcode_exportfunction",
                "parentNodeId": "qrcodemenu",
                "privilegeCode": "qrcode_export",
                "privilegeName": "导出",
                "isParent": "FALSE",
                "type": "function",
                "checked": "FALSE",
                "id": "qrcode_exportfunction",
                "parentId": "qrcodemenu",
                "text": "导出",
                "children": []
              },
              {
                "nodeId": "qrcode_bind_childfunction",
                "parentNodeId": "qrcodemenu",
                "privilegeCode": "qrcode_bind_child",
                "privilegeName": "绑定子码",
                "isParent": "FALSE",
                "type": "function",
                "checked": "FALSE",
                "id": "qrcode_bind_childfunction",
                "parentId": "qrcodemenu",
                "text": "绑定子码",
                "children": []
              },
              {
                "nodeId": "bind_batch_qrcodefunction",
                "parentNodeId": "qrcodemenu",
                "privilegeCode": "bind_batch_qrcode",
                "privilegeName": "批量绑定",
                "isParent": "FALSE",
                "type": "function",
                "checked": "FALSE",
                "id": "bind_batch_qrcodefunction",
                "parentId": "qrcodemenu",
                "text": "批量绑定",
                "children": []
              },
              {
                "nodeId": "materiel_addfunction",
                "parentNodeId": "qrcodemenu",
                "privilegeCode": "materiel_add",
                "privilegeName": "物料入库",
                "isParent": "FALSE",
                "type": "function",
                "checked": "FALSE",
                "id": "materiel_addfunction",
                "parentId": "qrcodemenu",
                "text": "物料入库",
                "children": []
              }
            ]
          },
          {
            "nodeId": "qr_code_reciept_auditmenu",
            "parentNodeId": "qr_code_managemenu",
            "privilegeCode": "qr_code_reciept_audit",
            "privilegeName": "授权码审核",
            "isParent": "FALSE",
            "type": "menu",
            "checked": "FALSE",
            "id": "qr_code_reciept_auditmenu",
            "parentId": "qr_code_managemenu",
            "text": "授权码审核",
            "children": [
              {
                "nodeId": "qr_code_reciept_audit_secondfunction",
                "parentNodeId": "qr_code_reciept_auditmenu",
                "privilegeCode": "qr_code_reciept_audit_second",
                "privilegeName": "授权码采购审核通过",
                "isParent": "FALSE",
                "type": "function",
                "checked": "FALSE",
                "id": "qr_code_reciept_audit_secondfunction",
                "parentId": "qr_code_reciept_auditmenu",
                "text": "授权码采购审核通过",
                "children": []
              },
              {
                "nodeId": "qr_code_reciept_reject_secondfunction",
                "parentNodeId": "qr_code_reciept_auditmenu",
                "privilegeCode": "qr_code_reciept_reject_second",
                "privilegeName": "授权码采购审核拒绝",
                "isParent": "FALSE",
                "type": "function",
                "checked": "FALSE",
                "id": "qr_code_reciept_reject_secondfunction",
                "parentId": "qr_code_reciept_auditmenu",
                "text": "授权码采购审核拒绝",
                "children": []
              },
              {
                "nodeId": "qr_code_reciept_audit_pagefunction",
                "parentNodeId": "qr_code_reciept_auditmenu",
                "privilegeCode": "qr_code_reciept_audit_page",
                "privilegeName": "授权码分页查询",
                "isParent": "FALSE",
                "type": "function",
                "checked": "FALSE",
                "id": "qr_code_reciept_audit_pagefunction",
                "parentId": "qr_code_reciept_auditmenu",
                "text": "授权码分页查询",
                "children": []
              },
              {
                "nodeId": "qr_code_reciept_audit_adminfunction",
                "parentNodeId": "qr_code_reciept_auditmenu",
                "privilegeCode": "qr_code_reciept_audit_admin",
                "privilegeName": "运营审核授权码权限",
                "isParent": "FALSE",
                "type": "function",
                "checked": "FALSE",
                "id": "qr_code_reciept_audit_adminfunction",
                "parentId": "qr_code_reciept_auditmenu",
                "text": "运营审核授权码权限",
                "children": []
              },
              {
                "nodeId": "qr_code_reciept_audit_agentfunction",
                "parentNodeId": "qr_code_reciept_auditmenu",
                "privilegeCode": "qr_code_reciept_audit_agent",
                "privilegeName": "代理商授权码审核权限",
                "isParent": "FALSE",
                "type": "function",
                "checked": "FALSE",
                "id": "qr_code_reciept_audit_agentfunction",
                "parentId": "qr_code_reciept_auditmenu",
                "text": "代理商授权码审核权限",
                "children": []
              },
              {
                "nodeId": "qr_code_reciept_audit_allfunction",
                "parentNodeId": "qr_code_reciept_auditmenu",
                "privilegeCode": "qr_code_reciept_audit_all",
                "privilegeName": "授权码审核",
                "isParent": "FALSE",
                "type": "function",
                "checked": "FALSE",
                "id": "qr_code_reciept_audit_allfunction",
                "parentId": "qr_code_reciept_auditmenu",
                "text": "授权码审核",
                "children": []
              }
            ]
          },
          {
            "nodeId": "qr_code_migratemenu",
            "parentNodeId": "qr_code_managemenu",
            "privilegeCode": "qr_code_migrate",
            "privilegeName": "授权码转移",
            "isParent": "FALSE",
            "type": "menu",
            "checked": "FALSE",
            "id": "qr_code_migratemenu",
            "parentId": "qr_code_managemenu",
            "text": "授权码转移",
            "children": [
              {
                "nodeId": "qr_code_migrate_distributefunction",
                "parentNodeId": "qr_code_migratemenu",
                "privilegeCode": "qr_code_migrate_distribute",
                "privilegeName": "授权码分配",
                "isParent": "FALSE",
                "type": "function",
                "checked": "FALSE",
                "id": "qr_code_migrate_distributefunction",
                "parentId": "qr_code_migratemenu",
                "text": "授权码分配",
                "children": []
              },
              {
                "nodeId": "qr_code_migrate_recoverfunction",
                "parentNodeId": "qr_code_migratemenu",
                "privilegeCode": "qr_code_migrate_recover",
                "privilegeName": "授权码上缴",
                "isParent": "FALSE",
                "type": "function",
                "checked": "FALSE",
                "id": "qr_code_migrate_recoverfunction",
                "parentId": "qr_code_migratemenu",
                "text": "授权码上缴",
                "children": []
              },
              {
                "nodeId": "qr_code_migrate_pagefunction",
                "parentNodeId": "qr_code_migratemenu",
                "privilegeCode": "qr_code_migrate_page",
                "privilegeName": "分页查询",
                "isParent": "FALSE",
                "type": "function",
                "checked": "FALSE",
                "id": "qr_code_migrate_pagefunction",
                "parentId": "qr_code_migratemenu",
                "text": "分页查询",
                "children": []
              },
              {
                "nodeId": "qr_code_migrate_downloadfunction",
                "parentNodeId": "qr_code_migratemenu",
                "privilegeCode": "qr_code_migrate_download",
                "privilegeName": "下载",
                "isParent": "FALSE",
                "type": "function",
                "checked": "FALSE",
                "id": "qr_code_migrate_downloadfunction",
                "parentId": "qr_code_migratemenu",
                "text": "下载",
                "children": []
              }
            ]
          }
        ]
      },
      {
        "nodeId": "customermenu",
        "parentNodeId": "rootmenu",
        "privilegeCode": "customer",
        "privilegeName": "我的商户",
        "isParent": "TRUE",
        "type": "menu",
        "checked": "FALSE",
        "id": "customermenu",
        "parentId": "rootmenu",
        "text": "我的商户",
        "children": [
          {
            "nodeId": "customerlistmenu",
            "parentNodeId": "customermenu",
            "privilegeCode": "customerlist",
            "privilegeName": "商户管理",
            "isParent": "FALSE",
            "type": "menu",
            "checked": "FALSE",
            "id": "customerlistmenu",
            "parentId": "customermenu",
            "text": "商户管理",
            "children": [
              {
                "nodeId": "customer_pagefunction",
                "parentNodeId": "customerlistmenu",
                "privilegeCode": "customer_page",
                "privilegeName": "分页查询",
                "isParent": "FALSE",
                "type": "function",
                "checked": "FALSE",
                "id": "customer_pagefunction",
                "parentId": "customerlistmenu",
                "text": "分页查询",
                "children": []
              },
              {
                "nodeId": "customer_addfunction",
                "parentNodeId": "customerlistmenu",
                "privilegeCode": "customer_add",
                "privilegeName": "新增",
                "isParent": "FALSE",
                "type": "function",
                "checked": "FALSE",
                "id": "customer_addfunction",
                "parentId": "customerlistmenu",
                "text": "新增",
                "children": []
              },
              {
                "nodeId": "customer_editfunction",
                "parentNodeId": "customerlistmenu",
                "privilegeCode": "customer_edit",
                "privilegeName": "修改",
                "isParent": "FALSE",
                "type": "function",
                "checked": "FALSE",
                "id": "customer_editfunction",
                "parentId": "customerlistmenu",
                "text": "修改",
                "children": []
              },
              {
                "nodeId": "customer_incomeBatchfunction",
                "parentNodeId": "customerlistmenu",
                "privilegeCode": "customer_incomeBatch",
                "privilegeName": "商户批量入网",
                "isParent": "FALSE",
                "type": "function",
                "checked": "FALSE",
                "id": "customer_incomeBatchfunction",
                "parentId": "customerlistmenu",
                "text": "商户批量入网",
                "children": []
              },
              {
                "nodeId": "customer_product_editfunction",
                "parentNodeId": "customerlistmenu",
                "privilegeCode": "customer_product_edit",
                "privilegeName": "商户产品设置",
                "isParent": "FALSE",
                "type": "function",
                "checked": "FALSE",
                "id": "customer_product_editfunction",
                "parentId": "customerlistmenu",
                "text": "商户产品设置",
                "children": []
              },
              {
                "nodeId": "customer_detailfunction",
                "parentNodeId": "customerlistmenu",
                "privilegeCode": "customer_detail",
                "privilegeName": "详情",
                "isParent": "FALSE",
                "type": "function",
                "checked": "FALSE",
                "id": "customer_detailfunction",
                "parentId": "customerlistmenu",
                "text": "详情",
                "children": []
              },
              {
                "nodeId": "customer_transferfunction",
                "parentNodeId": "customerlistmenu",
                "privilegeCode": "customer_transfer",
                "privilegeName": "转移",
                "isParent": "FALSE",
                "type": "function",
                "checked": "FALSE",
                "id": "customer_transferfunction",
                "parentId": "customerlistmenu",
                "text": "转移",
                "children": []
              },
              {
                "nodeId": "customer_exportfunction",
                "parentNodeId": "customerlistmenu",
                "privilegeCode": "customer_export",
                "privilegeName": "商户导出",
                "isParent": "FALSE",
                "type": "function",
                "checked": "FALSE",
                "id": "customer_exportfunction",
                "parentId": "customerlistmenu",
                "text": "商户导出",
                "children": []
              },
              {
                "nodeId": "customer_transBatchfunction",
                "parentNodeId": "customerlistmenu",
                "privilegeCode": "customer_transBatch",
                "privilegeName": "商户批量转移",
                "isParent": "FALSE",
                "type": "function",
                "checked": "FALSE",
                "id": "customer_transBatchfunction",
                "parentId": "customerlistmenu",
                "text": "商户批量转移",
                "children": []
              },
              {
                "nodeId": "customer_electronicOpenfunction",
                "parentNodeId": "customerlistmenu",
                "privilegeCode": "customer_electronicOpen",
                "privilegeName": "商户电票开通",
                "isParent": "FALSE",
                "type": "function",
                "checked": "FALSE",
                "id": "customer_electronicOpenfunction",
                "parentId": "customerlistmenu",
                "text": "商户电票开通",
                "children": []
              }
            ]
          },
          {
            "nodeId": "agent-customer-productmenu",
            "parentNodeId": "customermenu",
            "privilegeCode": "agent-customer-product",
            "privilegeName": "产品配置",
            "isParent": "FALSE",
            "type": "menu",
            "checked": "FALSE",
            "id": "agent-customer-productmenu",
            "parentId": "customermenu",
            "text": "产品配置",
            "children": [
              {
                "nodeId": "agent-customer-product_editfunction",
                "parentNodeId": "agent-customer-productmenu",
                "privilegeCode": "agent-customer-product_edit",
                "privilegeName": "产品模版配置",
                "isParent": "FALSE",
                "type": "function",
                "checked": "FALSE",
                "id": "agent-customer-product_editfunction",
                "parentId": "agent-customer-productmenu",
                "text": "产品模版配置",
                "children": []
              },
              {
                "nodeId": "agent-customer-product_queryfunction",
                "parentNodeId": "agent-customer-productmenu",
                "privilegeCode": "agent-customer-product_query",
                "privilegeName": "产品模版查询",
                "isParent": "FALSE",
                "type": "function",
                "checked": "FALSE",
                "id": "agent-customer-product_queryfunction",
                "parentId": "agent-customer-productmenu",
                "text": "产品模版查询",
                "children": []
              }
            ]
          },
          {
            "nodeId": "customerGoodsmenu",
            "parentNodeId": "customermenu",
            "privilegeCode": "customerGoods",
            "privilegeName": "商品管理",
            "isParent": "FALSE",
            "type": "menu",
            "checked": "FALSE",
            "id": "customerGoodsmenu",
            "parentId": "customermenu",
            "text": "商品管理",
            "children": []
          },
          {
            "nodeId": "customerInvoiceConfigmenu",
            "parentNodeId": "customermenu",
            "privilegeCode": "customerInvoiceConfig",
            "privilegeName": "开票配置",
            "isParent": "FALSE",
            "type": "menu",
            "checked": "FALSE",
            "id": "customerInvoiceConfigmenu",
            "parentId": "customermenu",
            "text": "开票配置",
            "children": []
          },
          {
            "nodeId": "customerProductmenu",
            "parentNodeId": "customermenu",
            "privilegeCode": "customerProduct",
            "privilegeName": "商户产品",
            "isParent": "FALSE",
            "type": "menu",
            "checked": "FALSE",
            "id": "customerProductmenu",
            "parentId": "customermenu",
            "text": "商户产品",
            "children": []
          }
        ]
      },
      {
        "nodeId": "statistical_managemenu",
        "parentNodeId": "rootmenu",
        "privilegeCode": "statistical_manage",
        "privilegeName": "统计管理",
        "isParent": "TRUE",
        "type": "menu",
        "checked": "FALSE",
        "id": "statistical_managemenu",
        "parentId": "rootmenu",
        "text": "统计管理",
        "children": [
          {
            "nodeId": "operator_logmenu",
            "parentNodeId": "statistical_managemenu",
            "privilegeCode": "operator_log",
            "privilegeName": "埋点管理",
            "isParent": "FALSE",
            "type": "menu",
            "checked": "FALSE",
            "id": "operator_logmenu",
            "parentId": "statistical_managemenu",
            "text": "埋点管理",
            "children": []
          },
          {
            "nodeId": "billrecord_chartmenu",
            "parentNodeId": "statistical_managemenu",
            "privilegeCode": "billrecord_chart",
            "privilegeName": "开票图表",
            "isParent": "FALSE",
            "type": "menu",
            "checked": "FALSE",
            "id": "billrecord_chartmenu",
            "parentId": "statistical_managemenu",
            "text": "开票图表",
            "children": []
          },
          {
            "nodeId": "operator_log_chartmenu",
            "parentNodeId": "statistical_managemenu",
            "privilegeCode": "operator_log_chart",
            "privilegeName": "埋点图表",
            "isParent": "FALSE",
            "type": "menu",
            "checked": "FALSE",
            "id": "operator_log_chartmenu",
            "parentId": "statistical_managemenu",
            "text": "埋点图表",
            "children": []
          }
        ]
      },
      {
        "nodeId": "product-mgmenu",
        "parentNodeId": "rootmenu",
        "privilegeCode": "product-mg",
        "privilegeName": "我的产品",
        "isParent": "TRUE",
        "type": "menu",
        "checked": "FALSE",
        "id": "product-mgmenu",
        "parentId": "rootmenu",
        "text": "我的产品",
        "children": [
          {
            "nodeId": "productmenu",
            "parentNodeId": "product-mgmenu",
            "privilegeCode": "product",
            "privilegeName": "产品管理",
            "isParent": "FALSE",
            "type": "menu",
            "checked": "FALSE",
            "id": "productmenu",
            "parentId": "product-mgmenu",
            "text": "产品管理",
            "children": [
              {
                "nodeId": "product_addfunction",
                "parentNodeId": "productmenu",
                "privilegeCode": "product_add",
                "privilegeName": "新增",
                "isParent": "FALSE",
                "type": "function",
                "checked": "FALSE",
                "id": "product_addfunction",
                "parentId": "productmenu",
                "text": "新增",
                "children": []
              },
              {
                "nodeId": "product_pagefunction",
                "parentNodeId": "productmenu",
                "privilegeCode": "product_page",
                "privilegeName": "分页查询",
                "isParent": "FALSE",
                "type": "function",
                "checked": "FALSE",
                "id": "product_pagefunction",
                "parentId": "productmenu",
                "text": "分页查询",
                "children": []
              },
              {
                "nodeId": "product_editfunction",
                "parentNodeId": "productmenu",
                "privilegeCode": "product_edit",
                "privilegeName": "修改产品",
                "isParent": "FALSE",
                "type": "function",
                "checked": "FALSE",
                "id": "product_editfunction",
                "parentId": "productmenu",
                "text": "修改产品",
                "children": []
              },
              {
                "nodeId": "product_falsefunction",
                "parentNodeId": "productmenu",
                "privilegeCode": "product_false",
                "privilegeName": "禁用",
                "isParent": "FALSE",
                "type": "function",
                "checked": "FALSE",
                "id": "product_falsefunction",
                "parentId": "productmenu",
                "text": "禁用",
                "children": []
              },
              {
                "nodeId": "product_truefunction",
                "parentNodeId": "productmenu",
                "privilegeCode": "product_true",
                "privilegeName": "启用",
                "isParent": "FALSE",
                "type": "function",
                "checked": "FALSE",
                "id": "product_truefunction",
                "parentId": "productmenu",
                "text": "启用",
                "children": []
              }
            ]
          }
        ]
      },
      {
        "nodeId": "bill-mgmenu",
        "parentNodeId": "rootmenu",
        "privilegeCode": "bill-mg",
        "privilegeName": "开票管理",
        "isParent": "TRUE",
        "type": "menu",
        "checked": "FALSE",
        "id": "bill-mgmenu",
        "parentId": "rootmenu",
        "text": "开票管理",
        "children": [
          {
            "nodeId": "billrecordmenu",
            "parentNodeId": "bill-mgmenu",
            "privilegeCode": "billrecord",
            "privilegeName": "开票记录",
            "isParent": "FALSE",
            "type": "menu",
            "checked": "FALSE",
            "id": "billrecordmenu",
            "parentId": "bill-mgmenu",
            "text": "开票记录",
            "children": [
              {
                "nodeId": "billrecord_pagefunction",
                "parentNodeId": "billrecordmenu",
                "privilegeCode": "billrecord_page",
                "privilegeName": "分页查询",
                "isParent": "FALSE",
                "type": "function",
                "checked": "FALSE",
                "id": "billrecord_pagefunction",
                "parentId": "billrecordmenu",
                "text": "分页查询",
                "children": []
              }
            ]
          },
          {
            "nodeId": "billcountcustomermenu",
            "parentNodeId": "bill-mgmenu",
            "privilegeCode": "billcountcustomer",
            "privilegeName": "达标详情",
            "isParent": "FALSE",
            "type": "menu",
            "checked": "FALSE",
            "id": "billcountcustomermenu",
            "parentId": "bill-mgmenu",
            "text": "达标详情",
            "children": [
              {
                "nodeId": "billcountcustomer_pagefunction",
                "parentNodeId": "billcountcustomermenu",
                "privilegeCode": "billcountcustomer_page",
                "privilegeName": "分页查询",
                "isParent": "FALSE",
                "type": "function",
                "checked": "FALSE",
                "id": "billcountcustomer_pagefunction",
                "parentId": "billcountcustomermenu",
                "text": "分页查询",
                "children": []
              },
              {
                "nodeId": "billcountcustomer_exportfunction",
                "parentNodeId": "billcountcustomermenu",
                "privilegeCode": "billcountcustomer_export",
                "privilegeName": "导出",
                "isParent": "FALSE",
                "type": "function",
                "checked": "FALSE",
                "id": "billcountcustomer_exportfunction",
                "parentId": "billcountcustomermenu",
                "text": "导出",
                "children": []
              }
            ]
          },
          {
            "nodeId": "billcountagentmenu",
            "parentNodeId": "bill-mgmenu",
            "privilegeCode": "billcountagent",
            "privilegeName": "开票统计",
            "isParent": "FALSE",
            "type": "menu",
            "checked": "FALSE",
            "id": "billcountagentmenu",
            "parentId": "bill-mgmenu",
            "text": "开票统计",
            "children": [
              {
                "nodeId": "billcountagent_pagefunction",
                "parentNodeId": "billcountagentmenu",
                "privilegeCode": "billcountagent_page",
                "privilegeName": "分页查询",
                "isParent": "FALSE",
                "type": "function",
                "checked": "FALSE",
                "id": "billcountagent_pagefunction",
                "parentId": "billcountagentmenu",
                "text": "分页查询",
                "children": []
              },
              {
                "nodeId": "billcountagent_sumfunction",
                "parentNodeId": "billcountagentmenu",
                "privilegeCode": "billcountagent_sum",
                "privilegeName": "合计",
                "isParent": "FALSE",
                "type": "function",
                "checked": "FALSE",
                "id": "billcountagent_sumfunction",
                "parentId": "billcountagentmenu",
                "text": "合计",
                "children": []
              },
              {
                "nodeId": "billcountagent_exportfunction",
                "parentNodeId": "billcountagentmenu",
                "privilegeCode": "billcountagent_export",
                "privilegeName": "导出",
                "isParent": "FALSE",
                "type": "function",
                "checked": "FALSE",
                "id": "billcountagent_exportfunction",
                "parentId": "billcountagentmenu",
                "text": "导出",
                "children": []
              }
            ]
          },
          {
            "nodeId": "billcount_daymenu",
            "parentNodeId": "bill-mgmenu",
            "privilegeCode": "billcount_day",
            "privilegeName": "日开票详情",
            "isParent": "FALSE",
            "type": "menu",
            "checked": "FALSE",
            "id": "billcount_daymenu",
            "parentId": "bill-mgmenu",
            "text": "日开票详情",
            "children": [
              {
                "nodeId": "billcount_day_pagefunction",
                "parentNodeId": "billcount_daymenu",
                "privilegeCode": "billcount_day_page",
                "privilegeName": "分页查询",
                "isParent": "FALSE",
                "type": "function",
                "checked": "FALSE",
                "id": "billcount_day_pagefunction",
                "parentId": "billcount_daymenu",
                "text": "分页查询",
                "children": []
              },
              {
                "nodeId": "billcountday_exportfunction",
                "parentNodeId": "billcount_daymenu",
                "privilegeCode": "billcountday_export",
                "privilegeName": "导出",
                "isParent": "FALSE",
                "type": "function",
                "checked": "FALSE",
                "id": "billcountday_exportfunction",
                "parentId": "billcount_daymenu",
                "text": "导出",
                "children": []
              },
              {
                "nodeId": "billcount_day_downloadfunction",
                "parentNodeId": "billcount_daymenu",
                "privilegeCode": "billcount_day_download",
                "privilegeName": "下载",
                "isParent": "FALSE",
                "type": "function",
                "checked": "FALSE",
                "id": "billcount_day_downloadfunction",
                "parentId": "billcount_daymenu",
                "text": "下载",
                "children": []
              }
            ]
          }
        ]
      },
      {
        "nodeId": "profitmenu",
        "parentNodeId": "rootmenu",
        "privilegeCode": "profit",
        "privilegeName": "分润查询",
        "isParent": "TRUE",
        "type": "menu",
        "checked": "TRUE",
        "id": "profitmenu",
        "parentId": "rootmenu",
        "text": "分润查询",
        "children": [
          {
            "nodeId": "billprofitmenu",
            "parentNodeId": "profitmenu",
            "privilegeCode": "billprofit",
            "privilegeName": "快速开票分润",
            "isParent": "FALSE",
            "type": "menu",
            "checked": "TRUE",
            "id": "billprofitmenu",
            "parentId": "profitmenu",
            "text": "快速开票分润",
            "children": [
              {
                "nodeId": "billprofit_pagefunction",
                "parentNodeId": "billprofitmenu",
                "privilegeCode": "billprofit_page",
                "privilegeName": "分页查询",
                "isParent": "FALSE",
                "type": "function",
                "checked": "FALSE",
                "id": "billprofit_pagefunction",
                "parentId": "billprofitmenu",
                "text": "分页查询",
                "children": []
              },
              {
                "nodeId": "billprofit_sumfunction",
                "parentNodeId": "billprofitmenu",
                "privilegeCode": "billprofit_sum",
                "privilegeName": "合计",
                "isParent": "FALSE",
                "type": "function",
                "checked": "TRUE",
                "id": "billprofit_sumfunction",
                "parentId": "billprofitmenu",
                "text": "合计",
                "children": []
              }
            ]
          }
        ]
      },
      {
        "nodeId": "versionManagermenu",
        "parentNodeId": "rootmenu",
        "privilegeCode": "versionManager",
        "privilegeName": "版本控制",
        "isParent": "TRUE",
        "type": "menu",
        "checked": "TRUE",
        "id": "versionManagermenu",
        "parentId": "rootmenu",
        "text": "版本控制",
        "children": [
          {
            "nodeId": "versionCommandmenu",
            "parentNodeId": "versionManagermenu",
            "privilegeCode": "versionCommand",
            "privilegeName": "版本管理",
            "isParent": "FALSE",
            "type": "menu",
            "checked": "TRUE",
            "id": "versionCommandmenu",
            "parentId": "versionManagermenu",
            "text": "版本管理",
            "children": [
              {
                "nodeId": "versionCommand_pagefunction",
                "parentNodeId": "versionCommandmenu",
                "privilegeCode": "versionCommand_page",
                "privilegeName": "分页查询",
                "isParent": "FALSE",
                "type": "function",
                "checked": "FALSE",
                "id": "versionCommand_pagefunction",
                "parentId": "versionCommandmenu",
                "text": "分页查询",
                "children": []
              },
              {
                "nodeId": "versionCommand_addfunction",
                "parentNodeId": "versionCommandmenu",
                "privilegeCode": "versionCommand_add",
                "privilegeName": "新增",
                "isParent": "FALSE",
                "type": "function",
                "checked": "FALSE",
                "id": "versionCommand_addfunction",
                "parentId": "versionCommandmenu",
                "text": "新增",
                "children": []
              },
              {
                "nodeId": "versionCommand_editfunction",
                "parentNodeId": "versionCommandmenu",
                "privilegeCode": "versionCommand_edit",
                "privilegeName": "修改",
                "isParent": "FALSE",
                "type": "function",
                "checked": "TRUE",
                "id": "versionCommand_editfunction",
                "parentId": "versionCommandmenu",
                "text": "修改",
                "children": []
              }
            ]
          }
        ]
      }
    ]
  }
]